[{"name":"Fiáth Dániel","email":"afiath.d@gmail.com","tel":"06321234567","selectedWorker":"5","selectedGen":"man","project":"cut_wash_dry_finish","projectName":"Mosás - vágás - szárítás-Mosás - vágás - szárítás","selectedDate":"2024-02-05","selectedTime":"13:20:00-14:00:00","duration":"40","id":1},{"name":"Kovács Sándor","email":"sanyi@mail.hu","tel":"0612345678","selectedWorker":"2","selectedGen":"man","project":"boy","projectName":"Kisfiú hajvágás-Kisfiú hajvágás","selectedDate":"2024-02-05","selectedTime":"11:20:00-11:40:00","duration":"20","price":"4000","id":5},{"name":"Nagy Zsombor","email":"zsombori@mail.hu","tel":"0612345678","selectedWorker":"2","selectedGen":"man","project":"boy","projectName":"Kisfiú hajvágás-Kisfiú hajvágás","selectedDate":"2024-02-05","selectedTime":"10:00:00-10:20:00","duration":"20","id":6,"price":"9000"},{"name":"juliska","email":"sanyi@mail.hu","tel":"0612345678","selectedWorker":"4","selectedGen":"woman","project":"straightening-long","projectName":"Haj egyenesítés-Hosszú","selectedDate":"2024-02-05","selectedTime":"10:00:00-10:30:00","duration":"30","price":"4500","id":8},{"name":"ilonka","email":"sanyi@mail.hu","tel":"0612345678","selectedWorker":"5","selectedGen":"woman","project":"wash_cut_dry-medium","projectName":"Mosás - vágás - szárítás-Közepes","selectedDate":"2024-02-05","selectedTime":"14:00:00-15:00:00","duration":"60","price":"6800","id":9},{"name":"Tóth János","email":"jani@mail.hu","tel":"0612345678","selectedWorker":"3","selectedGen":"man","project":"cut","projectName":"Vágás-Vágás","selectedDate":"2024-02-05","selectedTime":"12:20:00-12:40:00","duration":"20","price":"4000","id":10},{"name":"Mirtild","email":"mirtold@mail.hu","tel":"0612345678","selectedWorker":"4","selectedGen":"woman","project":"straightening-long","projectName":"Haj egyenesítés-Hosszú","selectedDate":"2024-02-05","selectedTime":"10:30:00-11:00:00","duration":"30","price":"4500","id":11},{"name":"mária","email":"mari@mail.hu","tel":"0612345678","selectedWorker":"1","selectedGen":"woman","project":"curvy_cut-short","projectName":"Göndör haj vágás-Rövid","selectedDate":"2024-02-05","selectedTime":"13:20:00-14:00:00","duration":"40","price":"7100","id":12},{"name":"aranka","email":"aranka@mail.hu","tel":"0612345678","selectedWorker":"4","selectedGen":"woman","project":"curvy_cut-long","projectName":"Göndör haj vágás-Hosszú","selectedDate":"2024-02-05","selectedTime":"11:00:00-12:00:00","duration":"60","price":"9500","id":13},{"name":"Márió","email":"marimail.hu","tel":"0612345678","selectedWorker":"3","selectedGen":"man","project":"cut_wash_dry_finish","projectName":"Mosás - vágás - szárítás-Mosás - vágás - szárítás","selectedDate":"2024-02-05","selectedTime":"13:20:00-14:00:00","duration":"40","price":"4500","id":14},{"name":"geri","email":"geri@mail.hu","tel":"0612345678","selectedWorker":"2","selectedGen":"man","project":"boy","projectName":"Kisfiú hajvágás-Kisfiú hajvágás","selectedDate":"2024-02-05","selectedTime":"13:00:00-13:20:00","duration":"20","price":"4000","id":15},{"name":"sanyi","email":"sanyi@mail.hu","tel":"0612345678","selectedWorker":"4","selectedGen":"woman","project":"girl","projectName":"Kislány hajvágás-Kislány hajvágás","selectedDate":"2024-02-05","selectedTime":"8:00:00-08:30:00","duration":"30","price":"4000","id":16},{"name":"sanyi","email":"sanyi@mail.hu","tel":"06302145784","selectedWorker":"1","selectedGen":"man","project":"cut_wash_dry_finish","projectName":"Mosás - vágás - szárítás-Mosás - vágás - szárítás","selectedDate":"2024-02-05","selectedTime":"9:20:00-10:00:00","duration":"40","price":"4500","id":18},{"name":"sarolta","email":"sarolt@mail.hu","tel":"06202345678","selectedWorker":"5","selectedGen":"woman","project":"curvy_cut-medium","projectName":"Göndör haj vágás-Közepes","selectedDate":"2024-02-05","selectedTime":"15:50:00-16:40:00","duration":"50","price":"8500","id":19}]